biotrackr-0.1.0.dist-info/METADATA
biotrackr-0.1.0.dist-info/WHEEL
biotrackr-0.1.0.dist-info/entry_points.txt
biotrackr/__init__.py
biotrackr/__main__.py
biotrackr/cli.py
biotrackr/config/__init__.py
biotrackr/config/base.yaml
biotrackr/core/__init__.py
biotrackr/core/digest.py
biotrackr/core/fetch_bioconductor_release.py
biotrackr/core/fetch_github.py
biotrackr/core/fetch_papers.py
biotrackr/database.py
biotrackr/models.py
biotrackr/templates/report.html.j2
biotrackr-0.1.0.dist-info/RECORD
