Metadata-Version: 2.1
Name: biotrackr
Version: 0.1.0
Summary: This package is used to get updates on bio-related papers and softwares.
Author-Email: Matteo Miotto <miotsdata@gmail.com>
License: MIT
Requires-Python: >=3.10
Requires-Dist: pyyaml>=6.0.3
Requires-Dist: requests>=2.32.5
Requires-Dist: Jinja2>=3.1.6
Requires-Dist: platformdirs>=4.5.0
Requires-Dist: sqlalchemy>=2.0.44
